pysparkutilities/__init__.py
pysparkutilities/config.py
pysparkutilities/datastorage.py
pysparkutilities/ds_initializer.py
pysparkutilities/filesystem.py
pysparkutilities/hdfs.py
pysparkutilities/hive.py
pysparkutilities/minio.py
pysparkutilities/mongo.py
pysparkutilities/presto.py
pysparkutilities/spark_initializer.py
pysparkutilities/utils.py
pysparkutilities/model/__init__.py
pysparkutilities/model/filesystem.py
pysparkutilities/model/hdfs.py
pysparkutilities/model/minio.py
pysparkutilities/model/model.py
pyspark_utilities-0.0.39.dist-info/METADATA
pyspark_utilities-0.0.39.dist-info/WHEEL
pyspark_utilities-0.0.39.dist-info/top_level.txt
pyspark_utilities-0.0.39.dist-info/RECORD
